actsnclass/__init__.py
actsnclass/bazin.py
actsnclass/build_snpcc_canonical.py
actsnclass/classifiers.py
actsnclass/database.py
actsnclass/fit_lightcurves.py
actsnclass/learn_loop.py
actsnclass/metrics.py
actsnclass/plot_results.py
actsnclass/query_strategies.py
actsnclass/time_domain.py
actsnclass/time_domain_loop.py
actsnclass/scripts/__init__.py
actsnclass/scripts/build_canonical.py
actsnclass/scripts/build_time_domain.py
actsnclass/scripts/fit_dataset.py
actsnclass/scripts/make_metrics_plots.py
actsnclass/scripts/run_loop.py
actsnclass/scripts/run_time_domain.py
actsnclass-1.3.1.dist-info/licenses/LICENSE
actsnclass-1.3.1.dist-info/METADATA
actsnclass-1.3.1.dist-info/WHEEL
actsnclass-1.3.1.dist-info/entry_points.txt
actsnclass-1.3.1.dist-info/top_level.txt
actsnclass-1.3.1.dist-info/RECORD
