Metadata-Version: 2.4
Name: actsnclass
Version: 1.3.1
Summary: Active Learning for Supernova Photometric Classification
Author-email: "Emille E. O. Ishida" <emille@cosmostatistics-initiative.org>
License-Expression: GPL-3.0-or-later
Requires-Python: >=3.12
License-File: LICENSE
Requires-Dist: numpy>=1.17.0
Requires-Dist: pandas>=0.25.0
Requires-Dist: setuptools>=41.0.1
Requires-Dist: scipy>=1.3.0
Requires-Dist: scikit-learn>=0.20.3
Requires-Dist: seaborn>=0.9.0
Requires-Dist: sphinx-rtd-theme==1.2.2
Requires-Dist: matplotlib>=3.10.0
Dynamic: license-file
